admin_extra_urls/__init__.py
admin_extra_urls/api.py
admin_extra_urls/button.py
admin_extra_urls/checks.py
admin_extra_urls/config.py
admin_extra_urls/decorators.py
admin_extra_urls/mixins.py
admin_extra_urls/site.py
admin_extra_urls/utils.py
admin_extra_urls/__pycache__/__init__.cpython-39.pyc
admin_extra_urls/__pycache__/api.cpython-39.pyc
admin_extra_urls/__pycache__/button.cpython-39.pyc
admin_extra_urls/__pycache__/checks.cpython-39.pyc
admin_extra_urls/__pycache__/config.cpython-39.pyc
admin_extra_urls/__pycache__/decorators.cpython-39.pyc
admin_extra_urls/__pycache__/mixins.cpython-39.pyc
admin_extra_urls/__pycache__/utils.cpython-39.pyc
admin_extra_urls/templates/admin_extra_urls/action_page.html
admin_extra_urls/templates/admin_extra_urls/change_form.html
admin_extra_urls/templates/admin_extra_urls/change_list.html
admin_extra_urls/templates/admin_extra_urls/confirm.html
admin_extra_urls/templates/admin_extra_urls/grappelli/change_form.html
admin_extra_urls/templates/admin_extra_urls/grappelli/change_list.html
admin_extra_urls/templates/admin_extra_urls/grappelli/includes/change_form_buttons.html
admin_extra_urls/templates/admin_extra_urls/grappelli/includes/change_list_buttons.html
admin_extra_urls/templates/admin_extra_urls/includes/action_buttons.html
admin_extra_urls/templates/admin_extra_urls/includes/attrs.html
admin_extra_urls/templates/admin_extra_urls/includes/button.html
admin_extra_urls/templates/admin_extra_urls/includes/change_form_buttons.html
admin_extra_urls/templates/admin_extra_urls/includes/change_list_buttons.html
admin_extra_urls/templates/admin_extra_urls/includes/styles.html
admin_extra_urls/templatetags/__init__.py
admin_extra_urls/templatetags/extra_urls.py
admin_extra_urls/templatetags/__pycache__/__init__.cpython-39.pyc
admin_extra_urls/templatetags/__pycache__/extra_urls.cpython-39.pyc
templatetags/__init__.py
templatetags/extra_urls.py
django_admin_extra_urls-4.1.dist-info/LICENSE
django_admin_extra_urls-4.1.dist-info/METADATA
django_admin_extra_urls-4.1.dist-info/WHEEL
django_admin_extra_urls-4.1.dist-info/top_level.txt
django_admin_extra_urls-4.1.dist-info/RECORD
